mingo/__init__.py
mingo/__main__.py
mingo/main.py
mingo-0.0.7.dist-info/LICENSE
mingo-0.0.7.dist-info/METADATA
mingo-0.0.7.dist-info/WHEEL
mingo-0.0.7.dist-info/top_level.txt
mingo-0.0.7.dist-info/RECORD
