Metadata-Version: 2.1
Name: mingo
Version: 0.0.7
Summary: A Python project to get a list of programming languages from Wikipedia
Home-page: https://github.com/NicholasSynovic/mingo
Author: Nicholas M. Synovic
Author-email: nicholas.synovic@gmail.com
License: UNKNOWN
Project-URL: Bug Tracker, https://github.com/NicholasSynovic/mingo/issues
Platform: UNKNOWN
Classifier: Programming Language :: Python :: 3
Classifier: Operating System :: OS Independent
Requires-Python: >=3.9
License-File: LICENSE
Requires-Dist: bs4
Requires-Dist: lxml
Requires-Dist: requests
